{
  "resource": "Sensors",
  "resource_explanation": null,
  "http_method": "GET",
  "route": "/api/rest/private/system/sensors",
  "description": "get listing",
  "explanation": null,
  "parameters": [

  ],
  "response_fields": [

  ],
  "requests": [
    {
      "request_method": "GET",
      "request_path": "/api/rest/private/system/sensors",
      "request_body": null,
      "request_headers": {
        "Accept": "application/vnd.api+json",
        "Content-Type": "application/vnd.api+json",
        "Authorization": "eyJ0eXAiOiJKV1QiLCJhbGciOiJIUzI1NiJ9.eyJleHAiOjE1MDQ1ODE3NDEsInN1YiI6MTI2fQ.-S7-Tr6mFZ2LEjSSnwUx7FUQY4mF18BEy-w-r_pMzZc",
        "Host": "example.org",
        "Cookie": ""
      },
      "request_query_parameters": {
      },
      "request_content_type": "application/vnd.api+json",
      "response_status": 200,
      "response_status_text": "OK",
      "response_body": "{\"data\":[{\"id\":\"1\",\"type\":\"sensors\",\"links\":{\"self\":\"http://example.org/api/rest/private/system/sensors/1\"},\"attributes\":{\"name\":\"sensor1\",\"mode-id\":1,\"source-interface\":null,\"target-mac\":null,\"use-routing\":false,\"target-ip\":\"192.168.0.2\",\"source-ip\":\"192.168.0.1\"}},{\"id\":\"2\",\"type\":\"sensors\",\"links\":{\"self\":\"http://example.org/api/rest/private/system/sensors/2\"},\"attributes\":{\"name\":\"sensor2\",\"mode-id\":1,\"source-interface\":null,\"target-mac\":null,\"use-routing\":false,\"target-ip\":\"192.168.0.2\",\"source-ip\":\"192.168.0.1\"}}]}",
      "response_headers": {
        "X-Frame-Options": "SAMEORIGIN",
        "X-XSS-Protection": "1; mode=block",
        "X-Content-Type-Options": "nosniff",
        "Content-Type": "application/vnd.api+json",
        "ETag": "W/\"ff29104845e851430e72734f5492396a\"",
        "Cache-Control": "max-age=0, private, must-revalidate",
        "X-Request-Id": "56e4b67d-8804-40a6-9953-d363490d956c",
        "X-Runtime": "0.087200",
        "Content-Length": "526"
      },
      "response_content_type": "application/vnd.api+json",
      "curl": null
    }
  ]
}